MANIFEST.in
README.rst
setup.py
ringbuffer/__init__.py
ringbuffer/ring.py
ringbuffer.egg-info/PKG-INFO
ringbuffer.egg-info/SOURCES.txt
ringbuffer.egg-info/dependency_links.txt
ringbuffer.egg-info/top_level.txt