Metadata-Version: 1.1
Name: ringbuffer
Version: 0.0.2
Summary: Random access associative ring buffer
Home-page: UNKNOWN
Author: Martin Gergov
Author-email: martingergov1@gmail.com
License: MIT/X11
Download-URL: https://bitbucket.org/marto1/ringbuffer/
Keywords: ring buffer,container
Platform: UNKNOWN
Classifier: License :: OSI Approved :: MIT License
Classifier: Topic :: Utilities
Classifier: Programming Language :: Python :: 2.7
